{
  "name": "Onchain AI Skill Hub",
  "url": "https://skills.onchainai.fund",
  "generatedAt": "1970-01-01T00:00:00.000Z",
  "totalSkills": 252,
  "categories": {
    "Dev Tools / Agents": 25,
    "Google / Ads": 11,
    "Google / Analytics": 2,
    "Google / Cloud": 56,
    "Local / Web Services": 6,
    "Media / Devices": 22,
    "Productivity / Messaging": 16,
    "Solana / Blockchain": 101,
    "Utilities": 13
  },
  "endpoints": {
    "ui": "https://skills.onchainai.fund/skills",
    "catalog": "https://skills.onchainai.fund/api/skills.json",
    "catalogIndex": "https://skills.onchainai.fund/api/skills",
    "monetization": "https://skills.onchainai.fund/api/monetization.json",
    "commerceKitIntegration": "https://skills.onchainai.fund/integrations/commerce-kit-payment-button.tsx",
    "skillMetadata": "https://skills.onchainai.fund/api/skills/{skill}/metadata.json",
    "skillSource": "https://skills.onchainai.fund/api/skills/{skill}/SKILL.md",
    "skillVerification": "https://skills.onchainai.fund/api/skills/{skill}/verification.json",
    "onchainRegistry": "https://skills.onchainai.fund/.well-known/onchain-skill-registry.json"
  },
  "skillsSh": {
    "install": "npx skills add Solizardking/skills",
    "repoConfig": "skills.sh.json"
  },
  "verification": {
    "chain": "solana",
    "status": "anchor-ready",
    "merkleRoot": "sha256-ad239d17fb1d90233b1b4ae210cd4d8617cf9205e23ea2d8121bad2652da4f96",
    "catalogHash": "sha256-2a7ef9a4724f01fcd3310c5a8d637f6ef3efff081fd34cbf05ae56713cb52899"
  },
  "monetization": {
    "onchain": "Solana Pay tip URI per skill card",
    "offchain": "Optional checkout URL carried in api/monetization.json",
    "commerceKit": "@solana-commerce/kit PaymentButton integration"
  }
}
